pydynamix/__init__.py
pydynamix/__init__.pyi
pydynamix-0.1.0.post1.dist-info/licenses/LICENSE.txt
pydynamix-0.1.0.post1.dist-info/METADATA
pydynamix-0.1.0.post1.dist-info/WHEEL
pydynamix-0.1.0.post1.dist-info/top_level.txt
pydynamix-0.1.0.post1.dist-info/RECORD
