Metadata-Version: 2.4
Name: pydynamix
Version: 0.1.0.post1
Summary: Dynamic execution and code manipulation utilities for Python
Author: Kareem Hashash
License: Copyright © 2025 <copyright holders>
Classifier: Programming Language :: Python :: 3
Classifier: Programming Language :: Python :: 3 :: Only
Classifier: License :: OSI Approved :: MIT License
Classifier: Operating System :: OS Independent
Requires-Python: >=3.9
License-File: LICENSE.txt
Dynamic: license-file
